<Report>
  <Body>
    <Division ID="37153589-4350-4a57-a254-6e9d167bcd35" HtmlDiv="True" rdReportAuthorElementType="Visualization" Class="rd-report-author-element" rdGalleryPanelID="rdCustomDashboardPanel_70b1828780ec4f81ab1aa09e4e19f89b">
      <Division ID="divTitle_37153589-4350-4a57-a254-6e9d167bcd35" HtmlDiv="True">
        <Label ID="lblVisualizationTitle_37153589-4350-4a57-a254-6e9d167bcd35" Class="ThemeHeader" Caption="InformationSchema">
        </Label>
      </Division>
      <Division ID="divContent_37153589-4350-4a57-a254-6e9d167bcd35" HtmlDiv="True" Class="rd-report-author-element-content rd-scrollable-x">
        <DataTable ID="dtAnalysisGrid_636517937089525755" CellSpacing="1" Class="rdThemeDataTable rdAgDataTable" TableBorder="0" DraggableColumns="True" ResizableColumns="True" RememberSort="True" AccessibleHeaders="True" AccessibleSummary="AnalysisGrid DataTable" ColumnHeaderClass="rdThemeDataTableHeader" CaptionClass="rdThemeDataTableMainHeader" AjaxPaging="True" ParentAGSortArrows="True" Width="100" WidthScale="%">
          <InteractivePaging ShowPageNumber="True" Class="rdThemePaging rdAgPaging" IDnotSupportedHere="pagingTable" PageRowCount="20" HideWhenOnePage="True" Location="Top" CaptionType="Image" CurrentPageClass="rdThemePagingCurrent" FirstPageCaption="_Themes/NTrust/images/rdPageFirstDark.png" PreviousPageCaption="_Themes/NTrust/images/rdPagePreviousDark.png" NextPageCaption="_Themes/NTrust/images/rdPageNextDark.png" LastPageCaption="_Themes/NTrust/images/rdPageLastDark.png" NumberedPageCount="" />
          <DataTableColumn Header="Table Name" rdAgGeneratedColumn="True" ID="agCol_NewTable1_Table_Name" DataColumn="NewTable1_Table_Name" ColumnHeaderClass="rdAgQbColor1" Class="rdThemeDataTableCell">
            <Label ID="agCol_NewTable1_Table_Name" Caption="@Data.NewTable1_Table_Name~" Format="" />
            <SpaceForBorders DataColumn="NewTable1_Table_Name" />
            <DataColumnSort DataColumn="NewTable1_Table_Name" DataType="Text" OriginalDataColumn="NewTable1_Table_Name" OriginalDataType="Text" />
          </DataTableColumn>
          <DataTableColumn Header="Table Type" rdAgGeneratedColumn="True" ID="agCol_NewTable1_Table_Type" DataColumn="NewTable1_Table_Type" ColumnHeaderClass="rdAgQbColor1" Class="rdThemeDataTableCell">
            <Label ID="agCol_NewTable1_Table_Type" Caption="@Data.NewTable1_Table_Type~" Format="" />
            <SpaceForBorders DataColumn="NewTable1_Table_Type" />
            <DataColumnSort DataColumn="NewTable1_Table_Type" DataType="Text" OriginalDataColumn="NewTable1_Table_Type" OriginalDataType="Text" />
          </DataTableColumn>
          <DataTableColumn Header="Create Time" rdAgGeneratedColumn="True" ID="agCol_NewTable1_Create_Time" DataColumn="NewTable1_Create_Time" Class="rdThemeDataTableCell" ColumnHeaderClass="rdAgQbColor1">
            <Label ID="agCol_NewTable1_Create_Time" Caption="@Data.NewTable1_Create_Time~" Format="General Date" />
            <SpaceForBorders DataColumn="NewTable1_Create_Time" />
            <DataColumnSort DataColumn="NewTable1_Create_Time" DataType="DateTime" OriginalDataColumn="NewTable1_Create_Time" OriginalDataType="DateTime" />
          </DataTableColumn>
          <DataLayer Type="ActiveSQL" ConnectionID="DemoDataSource" MetadataID="nttestMetadata" SourceType="Query" Source="SELECT Table_Name,Table_Type,Create_Time&#xA;       FROM information_schema.tables&#xA;       WHERE table_schema = 'remaap_900021'&#xA;       ORDER BY table_name" QueryBuilderTableID="NewTable1" ErrorSessionVar="rdActiveSqlErrorMsg">
            <SqlColumn ID="NewTable1_Table_Name" DataColumn="Table_Name" DataType="Text" Caption="Table Name" />
            <SqlColumn ID="NewTable1_Table_Type" DataColumn="Table_Type" DataType="Text" Caption="Table Type" />
            <SqlColumn ID="NewTable1_Create_Time" DataColumn="Create_Time" DataType="DateTime" Caption="Create Time" />
          </DataLayer>
        </DataTable>
      </Division>
      <HtmlStyle border-style="none" />
    </Division>
  </Body>
  <StyleSheet StyleSheet="rdTemplate/rdReportAuthor/reportAuthor.css" />
</Report>